README.rst
setup.py
bin/mri_unet
mri_unet/data3D.py
mri_unet/mri_unet.py
mri_unet.egg-info/PKG-INFO
mri_unet.egg-info/SOURCES.txt
mri_unet.egg-info/dependency_links.txt
mri_unet.egg-info/not-zip-safe
mri_unet.egg-info/requires.txt
mri_unet.egg-info/top_level.txt