Metadata-Version: 1.0
Name: mri-unet
Version: 0.1
Summary: (Python) utility to train an unet model to do brain mri segmentation
Home-page: https://github.com/FNNDSC/mri_unet
Author: FNNDSC
Author-email: dev@babymri.org
License: MIT
Platform: UNKNOWN
